day2/__init__.py
day2/_version.py
day2/exceptions.py
day2/session.py
day2/auth/__init__.py
day2/auth/credentials.py
day2/client/__init__.py
day2/client/base.py
day2/client/config.py
day2/client/constants.py
day2/client/profile.py
day2/client/user_context.py
day2/models/__init__.py
day2/models/account.py
day2/models/assessment.py
day2/models/azure_account.py
day2/models/azure_assessment.py
day2/models/bot.py
day2/models/cost.py
day2/models/project.py
day2/models/report.py
day2/models/resource.py
day2/models/role.py
day2/models/tenant.py
day2/models/user.py
day2/resources/__init__.py
day2/resources/account.py
day2/resources/assessment.py
day2/resources/azure_account.py
day2/resources/azure_assessment.py
day2/resources/bot.py
day2/resources/cost.py
day2/resources/project.py
day2/resources/report.py
day2/resources/resource.py
day2/resources/role.py
day2/resources/tenant.py
day2/resources/user.py
day2/utils/__init__.py
day2/utils/helpers.py
day2-0.3.3.dist-info/licenses/LICENSE
day2_cli/__init__.py
day2_cli/cli.py
day2_cli/commands/__init__.py
day2_cli/commands/account.py
day2_cli/commands/assessment.py
day2_cli/commands/auth.py
day2_cli/commands/azure_account.py
day2_cli/commands/azure_assessment.py
day2_cli/commands/bot.py
day2_cli/commands/cost.py
day2_cli/commands/profile.py
day2_cli/commands/project.py
day2_cli/commands/report.py
day2_cli/commands/resource.py
day2_cli/commands/role.py
day2_cli/commands/tenant.py
day2_cli/commands/tenant_docs_cli.py
day2_cli/commands/user.py
day2_cli/utils/__init__.py
day2_cli/utils/context.py
day2_cli/utils/exit_codes.py
day2_cli/utils/formatters.py
day2_cli/utils/helpers.py
day2_cli/utils/output_formatter.py
day2-0.3.3.dist-info/METADATA
day2-0.3.3.dist-info/WHEEL
day2-0.3.3.dist-info/entry_points.txt
day2-0.3.3.dist-info/top_level.txt
day2-0.3.3.dist-info/RECORD
